neuralmap/__init__.py
neuralmap/__main__.py
neuralmap/rh.py
neuralmap/search.py
neuralmap/utilities/__init__.py
neuralmap/utilities/decorators.py
neuralmap/utilities/log.py
neuralmap_client-0.0.0.dist-info/LICENSE
neuralmap_client-0.0.0.dist-info/METADATA
neuralmap_client-0.0.0.dist-info/WHEEL
neuralmap_client-0.0.0.dist-info/top_level.txt
neuralmap_client-0.0.0.dist-info/RECORD
