Metadata-Version: 2.1
Name: neuralmap-client
Version: 0.0.0
Summary: Search and recommandation engines.
Home-page: https://docs.neuralmap.io
Author: Tensor AI
Author-email: tensorai221@gmail.com
License: MIT
Classifier: License :: OSI Approved :: MIT License
Classifier: Programming Language :: Python :: 3.10
Classifier: Operating System :: OS Independent
Requires-Python: >=3.10
License-File: LICENSE
Requires-Dist: aiohttp >=3.9.5
Requires-Dist: bson >=0.5.10
Provides-Extra: dev
Requires-Dist: pytest >=7.0 ; extra == 'dev'
Requires-Dist: twine >=4.0.2 ; extra == 'dev'
